blportopt/__init__.py
blportopt/black_litterman_model.py
blportopt/config.py
blportopt/data_utils.py
blportopt/fama_french_model.py
blportopt/optimizer.py
blportopt/portfolio_construction_BL.py
blportopt/portfolio_construction_FF.py
blportopt/trading_strategy.py
blportopt/views.py
blportopt-0.0.0.dist-info/LICENSE.txt
blportopt-0.0.0.dist-info/METADATA
blportopt-0.0.0.dist-info/WHEEL
blportopt-0.0.0.dist-info/RECORD
